{"nodes": [{"id": "app_state_service_appstateservice", "label": "AppStateService", "file_type": "code", "source_file": "frontend/src/app/services/app-state.service.ts", "source_location": "line 22", "source_url": null, "captured_at": null, "author": null, "contributor": null}], "edges": [{"source": "app_state_service_appstateservice", "target": "station_card_component_stationcardcomponent", "relation": "shares_data_with", "confidence": "INFERRED", "confidence_score": 0.85, "source_file": "frontend/src/app/services/app-state.service.ts", "source_location": "line 17", "weight": 0.85}, {"source": "app_state_service_appstateservice", "target": "route_panel_component_routepanelcomponent", "relation": "shares_data_with", "confidence": "INFERRED", "confidence_score": 0.85, "source_file": "frontend/src/app/services/app-state.service.ts", "source_location": "line 17", "weight": 0.85}, {"source": "app_state_service_appstateservice", "target": "config_settings", "relation": "conceptually_related_to", "confidence": "INFERRED", "confidence_score": 0.6, "source_file": "frontend/src/app/services/app-state.service.ts", "source_location": null, "weight": 0.6}, {"source": "app_state_service_appstateservice", "target": "stations_recommend_stations", "relation": "calls", "confidence": "INFERRED", "confidence_score": 0.9, "source_file": "frontend/src/app/services/app-state.service.ts", "source_location": "line 133", "weight": 0.9}, {"source": "app_state_service_appstateservice", "target": "stations_route_recommend", "relation": "calls", "confidence": "INFERRED", "confidence_score": 0.9, "source_file": "frontend/src/app/services/app-state.service.ts", "source_location": "line 180", "weight": 0.9}], "hyperedges": []}